[{"Name":"InformRecordTrackGoods","TableName":"InformRecord_Track_Goods","Description":"案件通報商品身檔","HasIHasCompany":true,"HasIHasTenant":true,"Project":null,"IsSync":false,"EntityItems":[{"Name":"informRecordTrackId","ColumnName":"InformRecord_Track_Id","Type":"Long","Length":null,"IsRequired":false,"InQuery":true,"InResponse":true,"InCreate":true,"Description":"頭檔"},{"Name":"goodsId","ColumnName":"Goods_Id","Type":"Long","Length":null,"IsRequired":false,"InQuery":true,"InResponse":true,"InCreate":true,"Description":"品項"},{"Name":"qty","ColumnName":"Qty","Type":"Integer","Length":null,"IsRequired":false,"InQuery":false,"InResponse":true,"InCreate":true,"Description":"數量"},{"Name":"costUnitPrice","ColumnName":"CostUnitPrice","Type":"Float","Length":null,"IsRequired":false,"InQuery":false,"InResponse":true,"InCreate":true,"Description":"成本單價"},{"Name":"saleUnitPrice","ColumnName":"SaleUnitPrice","Type":"Float","Length":null,"IsRequired":false,"InQuery":false,"InResponse":true,"InCreate":true,"Description":"銷貨單價"},{"Name":"brand","ColumnName":"Brand","Type":"String","Length":100,"IsRequired":false,"InQuery":false,"InResponse":true,"InCreate":true,"Description":"品牌規格"},{"Name":"memo","ColumnName":"Memo","Type":"String","Length":1000,"IsRequired":false,"InQuery":false,"InResponse":false,"InCreate":true,"Description":"備註"},{"Name":"companyId","ColumnName":"CompanyId","Type":"Long","Length":null,"IsRequired":false,"InQuery":true,"InResponse":false,"InCreate":false,"Description":"公司編號"},{"Name":"tenantId","ColumnName":"TenantId","Type":"Long","Length":null,"IsRequired":false,"InQuery":false,"InResponse":false,"InCreate":false,"Description":"集團編號"}]},{"Name":"InformRecordTrackFile","TableName":"InformRecord_Track_File","Description":"案件通報處理紀錄附加檔案","HasIHasCompany":true,"HasIHasTenant":true,"Project":null,"IsSync":false,"EntityItems":[{"Name":"informRecordTrackId","ColumnName":"InformRecord_Track_Id","Type":"Long","Length":null,"IsRequired":false,"InQuery":false,"InResponse":true,"InCreate":true,"Description":"頭檔"},{"Name":"codeInformFileType","ColumnName":"Code_InformFileType","Type":"Long","Length":null,"IsRequired":false,"InQuery":true,"InResponse":true,"InCreate":true,"Description":"檔案類別"},{"Name":"fileId","ColumnName":"File_Id","Type":"Long","Length":null,"IsRequired":false,"InQuery":false,"InResponse":true,"InCreate":true,"Description":"附檔上傳"},{"Name":"memo","ColumnName":"Memo","Type":"String","Length":1000,"IsRequired":false,"InQuery":false,"InResponse":false,"InCreate":true,"Description":"備註"},{"Name":"companyId","ColumnName":"CompanyId","Type":"Long","Length":null,"IsRequired":false,"InQuery":true,"InResponse":false,"InCreate":false,"Description":"公司編號"},{"Name":"tenantId","ColumnName":"TenantId","Type":"Long","Length":null,"IsRequired":false,"InQuery":false,"InResponse":false,"InCreate":false,"Description":"集團編號"}]}]
