[{"Name":"FacilitySetting","TableName":"FacilitySetting","Description":"重要設備項目","HasIHasCompany":true,"HasIHasTenant":true,"Project":null,"IsSync":false,"EntityItems":[{"Name":"companyId","ColumnName":"Company_Id","Type":"Long","Length":null,"IsRequired":false,"InQuery":true,"InResponse":false,"InCreate":false,"Description":"公司編號"},{"Name":"code","ColumnName":"Code","Type":"String","Length":20,"IsRequired":false,"InQuery":true,"InResponse":true,"InCreate":true,"Description":"重要設備編號"},{"Name":"name","ColumnName":"Name","Type":"String","Length":20,"IsRequired":false,"InQuery":true,"InResponse":true,"InCreate":true,"Description":"重要設備名稱"},{"Name":"codeFacilityItem","ColumnName":"Code_FacilityItem","Type":"Long","Length":null,"IsRequired":false,"InQuery":true,"InResponse":true,"InCreate":true,"Description":"重要設備類別"},{"Name":"memo","ColumnName":"Memo","Type":"String","Length":1000,"IsRequired":false,"InQuery":false,"InResponse":false,"InCreate":true,"Description":"備註"},{"Name":"tenantId","ColumnName":"TenantId","Type":"Long","Length":null,"IsRequired":false,"InQuery":false,"InResponse":false,"InCreate":false,"Description":"集團編號"}]},{"Name":"FacilitySettingOtherCode","TableName":"FacilitySetting_OtherCode","Description":"重要設備項目其他公司編碼","HasIHasCompany":true,"HasIHasTenant":true,"Project":null,"IsSync":false,"EntityItems":[{"Name":"facilitySettingId","ColumnName":"FacilitySetting_Id","Type":"Long","Length":null,"IsRequired":false,"InQuery":true,"InResponse":true,"InCreate":true,"Description":"頭檔"},{"Name":"otherCompanyId","ColumnName":"otherCompany_Id","Type":"String","Length":50,"IsRequired":false,"InQuery":false,"InResponse":true,"InCreate":true,"Description":"其他公司"},{"Name":"otherCode","ColumnName":"OtherCode","Type":"String","Length":20,"IsRequired":false,"InQuery":false,"InResponse":true,"InCreate":true,"Description":"其他公司自編編號"},{"Name":"stopDate","ColumnName":"StopDate","Type":"Date","Length":null,"IsRequired":false,"InQuery":false,"InResponse":true,"InCreate":true,"Description":"停用日期"},{"Name":"memo","ColumnName":"Memo","Type":"String","Length":1000,"IsRequired":false,"InQuery":false,"InResponse":false,"InCreate":true,"Description":"備註"},{"Name":"companyId","ColumnName":"CompanyId","Type":"Long","Length":null,"IsRequired":false,"InQuery":true,"InResponse":false,"InCreate":false,"Description":"公司編號"},{"Name":"tenantId","ColumnName":"TenantId","Type":"Long","Length":null,"IsRequired":false,"InQuery":false,"InResponse":false,"InCreate":false,"Description":"集團編號"}]},{"Name":"FacilityItem","TableName":"FacilityItem","Description":"大樓設備管理","HasIHasCompany":true,"HasIHasTenant":true,"Project":null,"IsSync":false,"EntityItems":[{"Name":"companyId","ColumnName":"Company_Id","Type":"Long","Length":null,"IsRequired":false,"InQuery":true,"InResponse":false,"InCreate":false,"Description":"公司編號"},{"Name":"buildingId","ColumnName":"Building_Id","Type":"Long","Length":null,"IsRequired":false,"InQuery":true,"InResponse":true,"InCreate":true,"Description":"大樓"},{"Name":"publicAreaId","ColumnName":"PublicArea_Id","Type":"Long","Length":null,"IsRequired":false,"InQuery":false,"InResponse":true,"InCreate":true,"Description":"公共空間ID"},{"Name":"houseId","ColumnName":"House_Id","Type":"Long","Length":null,"IsRequired":false,"InQuery":false,"InResponse":true,"InCreate":true,"Description":"戶號"},{"Name":"facilitySettingId","ColumnName":"FacilitySetting_Id","Type":"Long","Length":null,"IsRequired":false,"InQuery":true,"InResponse":true,"InCreate":true,"Description":"重要設備ID"},{"Name":"code","ColumnName":"Code","Type":"String","Length":20,"IsRequired":false,"InQuery":true,"InResponse":true,"InCreate":true,"Description":"大樓設備編號"},{"Name":"name","ColumnName":"Name","Type":"String","Length":20,"IsRequired":false,"InQuery":true,"InResponse":true,"InCreate":true,"Description":"大樓設備名稱"},{"Name":"bimCode","ColumnName":"BimCode","Type":"String","Length":300,"IsRequired":false,"InQuery":false,"InResponse":true,"InCreate":true,"Description":"BIM元件"},{"Name":"ip","ColumnName":"IP","Type":"String","Length":20,"IsRequired":false,"InQuery":false,"InResponse":true,"InCreate":true,"Description":"IP"},{"Name":"url","ColumnName":"URL","Type":"String","Length":300,"IsRequired":false,"InQuery":false,"InResponse":true,"InCreate":true,"Description":"控制URL"},{"Name":"interCom","ColumnName":"InterCom","Type":"String","Length":300,"IsRequired":false,"InQuery":false,"InResponse":true,"InCreate":true,"Description":"對講機"},{"Name":"memo","ColumnName":"Memo","Type":"String","Length":1000,"IsRequired":false,"InQuery":false,"InResponse":false,"InCreate":true,"Description":"備註"},{"Name":"tenantId","ColumnName":"TenantId","Type":"Long","Length":null,"IsRequired":false,"InQuery":false,"InResponse":false,"InCreate":false,"Description":"集團編號"}]},{"Name":"CheckSetting","TableName":"CheckSetting","Description":"公司定期保養設定","HasIHasCompany":true,"HasIHasTenant":true,"Project":null,"IsSync":false,"EntityItems":[{"Name":"companyId","ColumnName":"Company_Id","Type":"Long","Length":null,"IsRequired":false,"InQuery":true,"InResponse":false,"InCreate":false,"Description":"公司編號"},{"Name":"codeCheckType","ColumnName":"Code_CheckType","Type":"Long","Length":null,"IsRequired":false,"InQuery":true,"InResponse":true,"InCreate":true,"Description":"設定類別"},{"Name":"ord","ColumnName":"Ord","Type":"Integer","Length":null,"IsRequired":false,"InQuery":false,"InResponse":true,"InCreate":true,"Description":"順序"},{"Name":"name","ColumnName":"Name","Type":"String","Length":20,"IsRequired":false,"InQuery":true,"InResponse":true,"InCreate":true,"Description":"設定名稱"},{"Name":"checkMonth","ColumnName":"CheckMonth","Type":"String","Length":10,"IsRequired":false,"InQuery":false,"InResponse":true,"InCreate":true,"Description":"檢查起始月份"},{"Name":"codeCheckPeriod","ColumnName":"Code_CheckPeriod","Type":"Long","Length":null,"IsRequired":false,"InQuery":false,"InResponse":true,"InCreate":true,"Description":"檢查週期"},{"Name":"checkDay","ColumnName":"CheckDay","Type":"String","Length":10,"IsRequired":false,"InQuery":false,"InResponse":true,"InCreate":true,"Description":"指定檢查日"},{"Name":"dutySettingId","ColumnName":"DutySetting_Id","Type":"Long","Length":null,"IsRequired":false,"InQuery":false,"InResponse":true,"InCreate":true,"Description":"休假類別"},{"Name":"checkTime","ColumnName":"CheckTime","Type":"String","Length":10,"IsRequired":false,"InQuery":false,"InResponse":true,"InCreate":true,"Description":"指定檢查時間"},{"Name":"licenseTypeId","ColumnName":"LicenseType_Id","Type":"Long","Length":null,"IsRequired":false,"InQuery":false,"InResponse":true,"InCreate":true,"Description":"定檢證照類別ID"},{"Name":"outSource","ColumnName":"OutSource","Type":"Boolean","Length":null,"IsRequired":false,"InQuery":false,"InResponse":true,"InCreate":true,"Description":"委外"},{"Name":"supplierId","ColumnName":"Supplier_Id","Type":"Long","Length":null,"IsRequired":false,"InQuery":true,"InResponse":true,"InCreate":true,"Description":"廠商"},{"Name":"operatingDocId","ColumnName":"OperatingDoc_Id","Type":"Long","Length":null,"IsRequired":false,"InQuery":false,"InResponse":true,"InCreate":true,"Description":"說明文件"},{"Name":"url","ColumnName":"Url","Type":"String","Length":300,"IsRequired":false,"InQuery":false,"InResponse":true,"InCreate":true,"Description":"連結網址"},{"Name":"deptId","ColumnName":"Dept_Id","Type":"Long","Length":null,"IsRequired":false,"InQuery":false,"InResponse":true,"InCreate":true,"Description":"權責部門"},{"Name":"memo","ColumnName":"Memo","Type":"String","Length":1000,"IsRequired":false,"InQuery":false,"InResponse":true,"InCreate":true,"Description":"注意事項"},{"Name":"startDate","ColumnName":"StartDate","Type":"Date","Length":null,"IsRequired":false,"InQuery":false,"InResponse":true,"InCreate":true,"Description":"生效日期"},{"Name":"endDate","ColumnName":"EndDate","Type":"Date","Length":null,"IsRequired":false,"InQuery":false,"InResponse":true,"InCreate":true,"Description":"停用日期"},{"Name":"released","ColumnName":"Released","Type":"Boolean","Length":null,"IsRequired":false,"InQuery":false,"InResponse":true,"InCreate":true,"Description":"上架"},{"Name":"tenantId","ColumnName":"TenantId","Type":"Long","Length":null,"IsRequired":false,"InQuery":false,"InResponse":false,"InCreate":false,"Description":"集團編號"}]},{"Name":"CheckSettingItem","TableName":"CheckSetting_Item","Description":"公司定期保養項目設定","HasIHasCompany":true,"HasIHasTenant":true,"Project":null,"IsSync":false,"EntityItems":[{"Name":"checkSettingId","ColumnName":"CheckSetting_Id","Type":"Long","Length":null,"IsRequired":false,"InQuery":true,"InResponse":true,"InCreate":true,"Description":"頭檔ID"},{"Name":"pid","ColumnName":"Pid","Type":"Long","Length":null,"IsRequired":false,"InQuery":false,"InResponse":true,"InCreate":true,"Description":"上階ID"},{"Name":"ord","ColumnName":"Ord","Type":"Integer","Length":null,"IsRequired":false,"InQuery":false,"InResponse":true,"InCreate":true,"Description":"順序"},{"Name":"code","ColumnName":"Code","Type":"String","Length":20,"IsRequired":false,"InQuery":true,"InResponse":true,"InCreate":true,"Description":"代號"},{"Name":"name","ColumnName":"Name","Type":"String","Length":20,"IsRequired":false,"InQuery":true,"InResponse":true,"InCreate":true,"Description":"項目名稱"},{"Name":"standardValue","ColumnName":"StandardValue","Type":"String","Length":300,"IsRequired":false,"InQuery":false,"InResponse":true,"InCreate":true,"Description":"標準值"},{"Name":"defaultValue","ColumnName":"DefaultValue","Type":"String","Length":300,"IsRequired":false,"InQuery":false,"InResponse":true,"InCreate":true,"Description":"預設值"},{"Name":"must","ColumnName":"Must","Type":"Boolean","Length":null,"IsRequired":false,"InQuery":false,"InResponse":true,"InCreate":true,"Description":"必要/非必要"},{"Name":"qty","ColumnName":"Qty","Type":"Integer","Length":null,"IsRequired":false,"InQuery":false,"InResponse":true,"InCreate":true,"Description":"數量"},{"Name":"memo","ColumnName":"Memo","Type":"String","Length":1000,"IsRequired":false,"InQuery":false,"InResponse":true,"InCreate":true,"Description":"說明"},{"Name":"disable","ColumnName":"Disable","Type":"Boolean","Length":null,"IsRequired":false,"InQuery":false,"InResponse":true,"InCreate":true,"Description":"停用"},{"Name":"companyId","ColumnName":"CompanyId","Type":"Long","Length":null,"IsRequired":false,"InQuery":true,"InResponse":false,"InCreate":false,"Description":"公司編號"},{"Name":"tenantId","ColumnName":"TenantId","Type":"Long","Length":null,"IsRequired":false,"InQuery":false,"InResponse":false,"InCreate":false,"Description":"集團編號"}]},{"Name":"CheckSettingItemTime","TableName":"CheckSetting_Item_Time","Description":"定期保養項目時限設定","HasIHasCompany":true,"HasIHasTenant":true,"Project":null,"IsSync":false,"EntityItems":[{"Name":"checkSettingItemId","ColumnName":"CheckSetting_Item_Id","Type":"Long","Length":null,"IsRequired":false,"InQuery":true,"InResponse":true,"InCreate":true,"Description":"頭檔"},{"Name":"codeCheckTimeType","ColumnName":"Code_CheckTimeType","Type":"Long","Length":null,"IsRequired":false,"InQuery":true,"InResponse":true,"InCreate":true,"Description":"時限類別"},{"Name":"hourLimit","ColumnName":"HourLimit","Type":"Float","Length":null,"IsRequired":false,"InQuery":false,"InResponse":true,"InCreate":true,"Description":"時限(小時)"},{"Name":"companyId","ColumnName":"CompanyId","Type":"Long","Length":null,"IsRequired":false,"InQuery":true,"InResponse":false,"InCreate":false,"Description":"公司編號"},{"Name":"tenantId","ColumnName":"TenantId","Type":"Long","Length":null,"IsRequired":false,"InQuery":false,"InResponse":false,"InCreate":false,"Description":"集團編號"}]},{"Name":"CheckSettingBuilding","TableName":"CheckSettingBuilding","Description":"大樓定期檢查設定","HasIHasCompany":true,"HasIHasTenant":true,"Project":null,"IsSync":false,"EntityItems":[{"Name":"buildingId","ColumnName":"Building_Id","Type":"Long","Length":null,"IsRequired":false,"InQuery":true,"InResponse":true,"InCreate":true,"Description":"大樓"},{"Name":"codeCheckType","ColumnName":"Code_CheckType","Type":"Long","Length":null,"IsRequired":false,"InQuery":true,"InResponse":true,"InCreate":true,"Description":"設定類別"},{"Name":"ord","ColumnName":"Ord","Type":"Integer","Length":null,"IsRequired":false,"InQuery":false,"InResponse":true,"InCreate":true,"Description":"順序"},{"Name":"name","ColumnName":"Name","Type":"String","Length":20,"IsRequired":false,"InQuery":true,"InResponse":true,"InCreate":true,"Description":"設定名稱"},{"Name":"checkMonth","ColumnName":"CheckMonth","Type":"String","Length":10,"IsRequired":false,"InQuery":false,"InResponse":true,"InCreate":true,"Description":"檢查起始月份"},{"Name":"codeCheckPeriod","ColumnName":"Code_CheckPeriod","Type":"Long","Length":null,"IsRequired":false,"InQuery":true,"InResponse":true,"InCreate":true,"Description":"檢查週期"},{"Name":"checkDay","ColumnName":"CheckDay","Type":"Date","Length":null,"IsRequired":false,"InQuery":false,"InResponse":true,"InCreate":true,"Description":"指定檢查日"},{"Name":"dutySettingId","ColumnName":"DutySetting_Id","Type":"Long","Length":null,"IsRequired":false,"InQuery":true,"InResponse":true,"InCreate":true,"Description":"休假類別"},{"Name":"checkTime","ColumnName":"CheckTime","Type":"String","Length":10,"IsRequired":false,"InQuery":false,"InResponse":true,"InCreate":true,"Description":"指定檢查時間"},{"Name":"licenseTypeId","ColumnName":"LicenseType_Id","Type":"Long","Length":null,"IsRequired":false,"InQuery":false,"InResponse":true,"InCreate":true,"Description":"定檢證照類別ID"},{"Name":"publicAreaId","ColumnName":"PublicArea_Id","Type":"Long","Length":null,"IsRequired":false,"InQuery":false,"InResponse":true,"InCreate":true,"Description":"公共空間ID"},{"Name":"outSource","ColumnName":"OutSource","Type":"Boolean","Length":null,"IsRequired":false,"InQuery":false,"InResponse":true,"InCreate":true,"Description":"委外"},{"Name":"supplierId","ColumnName":"Supplier_Id","Type":"Long","Length":null,"IsRequired":false,"InQuery":false,"InResponse":true,"InCreate":true,"Description":"廠商"},{"Name":"deptId","ColumnName":"Dept_Id","Type":"Long","Length":null,"IsRequired":false,"InQuery":false,"InResponse":true,"InCreate":true,"Description":"部門"},{"Name":"workCodeId","ColumnName":"WorkCode_Id","Type":"Long","Length":null,"IsRequired":false,"InQuery":false,"InResponse":true,"InCreate":true,"Description":"檢查人員"},{"Name":"operatingDocId","ColumnName":"OperatingDoc_Id","Type":"String","Length":null,"IsRequired":false,"InQuery":false,"InResponse":true,"InCreate":true,"Description":"說明文件"},{"Name":"url","ColumnName":"Url","Type":"String","Length":300,"IsRequired":false,"InQuery":false,"InResponse":true,"InCreate":true,"Description":"連結網址"},{"Name":"bimUrl","ColumnName":"BimUrl","Type":"String","Length":300,"IsRequired":false,"InQuery":false,"InResponse":true,"InCreate":true,"Description":"BIM連結網址"},{"Name":"bimCode","ColumnName":"BimCode","Type":"String","Length":300,"IsRequired":false,"InQuery":false,"InResponse":true,"InCreate":true,"Description":"BIM元件"},{"Name":"panoramaFileId","ColumnName":"panoramaFile_Id","Type":"Long","Length":null,"IsRequired":false,"InQuery":false,"InResponse":true,"InCreate":true,"Description":"實景導覽"},{"Name":"planFileUploadMapId","ColumnName":"planFile_UploadMap_Id","Type":"Long","Length":null,"IsRequired":false,"InQuery":false,"InResponse":true,"InCreate":true,"Description":"平面圖"},{"Name":"memo","ColumnName":"Memo","Type":"String","Length":1000,"IsRequired":false,"InQuery":false,"InResponse":true,"InCreate":true,"Description":"注意事項"},{"Name":"startDate","ColumnName":"StartDate","Type":"Date","Length":null,"IsRequired":false,"InQuery":false,"InResponse":true,"InCreate":true,"Description":"生效日期"},{"Name":"endDate","ColumnName":"EndDate","Type":"Date","Length":null,"IsRequired":false,"InQuery":false,"InResponse":true,"InCreate":true,"Description":"停用日期"},{"Name":"released","ColumnName":"Released","Type":"Boolean","Length":null,"IsRequired":false,"InQuery":false,"InResponse":true,"InCreate":true,"Description":"上架"},{"Name":"companyId","ColumnName":"CompanyId","Type":"Long","Length":null,"IsRequired":false,"InQuery":true,"InResponse":false,"InCreate":false,"Description":"公司編號"},{"Name":"tenantId","ColumnName":"TenantId","Type":"Long","Length":null,"IsRequired":false,"InQuery":false,"InResponse":false,"InCreate":false,"Description":"集團編號"}]},{"Name":"CheckSettingBuildingItem","TableName":"CheckSettingBuilding_Item","Description":"大樓定期檢查設定項目","HasIHasCompany":true,"HasIHasTenant":true,"Project":null,"IsSync":false,"EntityItems":[{"Name":"checkSettingBuildingId","ColumnName":"CheckSettingBuilding_Id","Type":"Long","Length":null,"IsRequired":false,"InQuery":true,"InResponse":true,"InCreate":true,"Description":"頭檔ID"},{"Name":"ord","ColumnName":"Ord","Type":"Integer","Length":null,"IsRequired":false,"InQuery":false,"InResponse":true,"InCreate":true,"Description":"順序"},{"Name":"checkSettingItemId","ColumnName":"CheckSetting_Item_Id","Type":"Long","Length":null,"IsRequired":false,"InQuery":true,"InResponse":true,"InCreate":true,"Description":"檢查項目"},{"Name":"standardValue","ColumnName":"StandardValue","Type":"String","Length":300,"IsRequired":false,"InQuery":false,"InResponse":true,"InCreate":true,"Description":"標準值"},{"Name":"defaultValue","ColumnName":"DefaultValue","Type":"String","Length":300,"IsRequired":false,"InQuery":false,"InResponse":true,"InCreate":true,"Description":"預設值"},{"Name":"must","ColumnName":"Must","Type":"Boolean","Length":null,"IsRequired":false,"InQuery":false,"InResponse":true,"InCreate":true,"Description":"必要/非必要"},{"Name":"qty","ColumnName":"Qty","Type":"Integer","Length":null,"IsRequired":false,"InQuery":false,"InResponse":true,"InCreate":true,"Description":"數量"},{"Name":"facilityItemId","ColumnName":"FacilityItem_Id","Type":"Long","Length":null,"IsRequired":false,"InQuery":false,"InResponse":true,"InCreate":true,"Description":"設備ID"},{"Name":"memo","ColumnName":"Memo","Type":"String","Length":1000,"IsRequired":false,"InQuery":false,"InResponse":true,"InCreate":true,"Description":"審查說明"},{"Name":"disable","ColumnName":"Disable","Type":"Boolean","Length":null,"IsRequired":false,"InQuery":false,"InResponse":true,"InCreate":true,"Description":"停用"},{"Name":"companyId","ColumnName":"CompanyId","Type":"Long","Length":null,"IsRequired":false,"InQuery":true,"InResponse":false,"InCreate":false,"Description":"公司編號"},{"Name":"tenantId","ColumnName":"TenantId","Type":"Long","Length":null,"IsRequired":false,"InQuery":false,"InResponse":false,"InCreate":false,"Description":"集團編號"}]},{"Name":"CheckSettingBuildingItemTime","TableName":"CheckSettingBuilding_Item_Time","Description":"大樓定期保養項目時限設定","HasIHasCompany":true,"HasIHasTenant":true,"Project":null,"IsSync":false,"EntityItems":[{"Name":"checkSettingBuildingItemId","ColumnName":"CheckSettingBuilding_Item_Id","Type":"Long","Length":null,"IsRequired":false,"InQuery":true,"InResponse":true,"InCreate":true,"Description":"頭檔"},{"Name":"codeCheckTimeType","ColumnName":"Code_CheckTimeType","Type":"Long","Length":null,"IsRequired":false,"InQuery":true,"InResponse":true,"InCreate":true,"Description":"時限類別"},{"Name":"hourLimit","ColumnName":"HourLimit","Type":"Float","Length":null,"IsRequired":false,"InQuery":false,"InResponse":true,"InCreate":true,"Description":"時限(小時)"},{"Name":"companyId","ColumnName":"CompanyId","Type":"Long","Length":null,"IsRequired":false,"InQuery":true,"InResponse":false,"InCreate":false,"Description":"公司編號"},{"Name":"tenantId","ColumnName":"TenantId","Type":"Long","Length":null,"IsRequired":false,"InQuery":false,"InResponse":false,"InCreate":false,"Description":"集團編號"}]},{"Name":"CheckSchedule","TableName":"CheckSchedule","Description":"大樓定期檢查排程檔","HasIHasCompany":true,"HasIHasTenant":true,"Project":null,"IsSync":false,"EntityItems":[{"Name":"buildingId","ColumnName":"Building_Id","Type":"Long","Length":null,"IsRequired":false,"InQuery":true,"InResponse":true,"InCreate":true,"Description":"大樓"},{"Name":"yearMonth","ColumnName":"YearMonth","Type":"String","Length":10,"IsRequired":false,"InQuery":false,"InResponse":true,"InCreate":true,"Description":"年月"},{"Name":"checkSettingBuildingId","ColumnName":"CheckSettingBuilding_Id","Type":"Long","Length":null,"IsRequired":false,"InQuery":true,"InResponse":true,"InCreate":true,"Description":"檢查項目ID"},{"Name":"expectedDate","ColumnName":"ExpectedDate","Type":"Date","Length":null,"IsRequired":false,"InQuery":false,"InResponse":true,"InCreate":true,"Description":"應檢日期"},{"Name":"outSource","ColumnName":"OutSource","Type":"Boolean","Length":null,"IsRequired":false,"InQuery":false,"InResponse":true,"InCreate":true,"Description":"委外"},{"Name":"supplierId","ColumnName":"Supplier_Id","Type":"Long","Length":null,"IsRequired":false,"InQuery":false,"InResponse":true,"InCreate":true,"Description":"廠商"},{"Name":"deptId","ColumnName":"Dept_Id","Type":"Long","Length":null,"IsRequired":false,"InQuery":false,"InResponse":true,"InCreate":true,"Description":"部門"},{"Name":"workCodeId","ColumnName":"WorkCode_Id","Type":"Long","Length":null,"IsRequired":false,"InQuery":false,"InResponse":true,"InCreate":true,"Description":"檢查人員"},{"Name":"companyId","ColumnName":"CompanyId","Type":"Long","Length":null,"IsRequired":false,"InQuery":true,"InResponse":false,"InCreate":false,"Description":"公司編號"},{"Name":"tenantId","ColumnName":"TenantId","Type":"Long","Length":null,"IsRequired":false,"InQuery":false,"InResponse":false,"InCreate":false,"Description":"集團編號"}]},{"Name":"CheckScheduleTrack","TableName":"CheckSchedule_Track","Description":"大樓定期檢查排程異動紀錄檔","HasIHasCompany":true,"HasIHasTenant":true,"Project":null,"IsSync":false,"EntityItems":[{"Name":"checkScheduleId","ColumnName":"CheckSchedule_Id","Type":"Long","Length":null,"IsRequired":false,"InQuery":true,"InResponse":true,"InCreate":true,"Description":"頭檔ID"},{"Name":"codeCheckScheduleMod","ColumnName":"Code_CheckScheduleMod","Type":"Long","Length":null,"IsRequired":false,"InQuery":true,"InResponse":true,"InCreate":true,"Description":"異動類別"},{"Name":"newExpectedDate","ColumnName":"NewExpectedDate","Type":"Date","Length":null,"IsRequired":false,"InQuery":false,"InResponse":true,"InCreate":true,"Description":"異動後應檢日期"},{"Name":"noticeFrom","ColumnName":"NoticeFrom","Type":"String","Length":20,"IsRequired":false,"InQuery":false,"InResponse":true,"InCreate":true,"Description":"通知人員"},{"Name":"memo","ColumnName":"Memo","Type":"String","Length":1000,"IsRequired":false,"InQuery":false,"InResponse":true,"InCreate":true,"Description":"說明"},{"Name":"companyId","ColumnName":"CompanyId","Type":"Long","Length":null,"IsRequired":false,"InQuery":true,"InResponse":false,"InCreate":false,"Description":"公司編號"},{"Name":"tenantId","ColumnName":"TenantId","Type":"Long","Length":null,"IsRequired":false,"InQuery":false,"InResponse":false,"InCreate":false,"Description":"集團編號"}]},{"Name":"CheckRecord","TableName":"CheckRecord","Description":"大樓定期檢查紀錄","HasIHasCompany":true,"HasIHasTenant":true,"Project":null,"IsSync":false,"EntityItems":[{"Name":"buildingId","ColumnName":"Building_Id","Type":"Long","Length":null,"IsRequired":false,"InQuery":true,"InResponse":true,"InCreate":true,"Description":"大樓"},{"Name":"checkDate","ColumnName":"CheckDate","Type":"Date","Length":null,"IsRequired":false,"InQuery":false,"InResponse":true,"InCreate":true,"Description":"檢查日期"},{"Name":"checkScheduleId","ColumnName":"CheckSchedule_Id","Type":"Long","Length":null,"IsRequired":false,"InQuery":false,"InResponse":true,"InCreate":true,"Description":"檢查排程ID"},{"Name":"checkSettingBuildingId","ColumnName":"CheckSettingBuilding_Id","Type":"String","Length":null,"IsRequired":false,"InQuery":true,"InResponse":true,"InCreate":true,"Description":"檢查項目ID"},{"Name":"licenseTypeId","ColumnName":"LicenseType_Id","Type":"Long","Length":null,"IsRequired":false,"InQuery":true,"InResponse":true,"InCreate":true,"Description":"定檢證照類別ID"},{"Name":"outSource","ColumnName":"OutSource","Type":"Boolean","Length":null,"IsRequired":false,"InQuery":false,"InResponse":true,"InCreate":true,"Description":"委外"},{"Name":"supplierId","ColumnName":"Supplier_Id","Type":"Long","Length":null,"IsRequired":false,"InQuery":true,"InResponse":true,"InCreate":true,"Description":"廠商"},{"Name":"deptId","ColumnName":"Dept_Id","Type":"Long","Length":null,"IsRequired":false,"InQuery":false,"InResponse":true,"InCreate":true,"Description":"部門"},{"Name":"workCodeId","ColumnName":"WorkCode_Id","Type":"Long","Length":null,"IsRequired":false,"InQuery":false,"InResponse":true,"InCreate":true,"Description":"檢查人員"},{"Name":"checklistFileUploadMapId","ColumnName":"checklistFile_UploadMap_Id","Type":"Long","Length":null,"IsRequired":false,"InQuery":false,"InResponse":true,"InCreate":true,"Description":"檢查表上傳"},{"Name":"fileUploadMapId","ColumnName":"File_UploadMap_Id","Type":"Long","Length":null,"IsRequired":false,"InQuery":false,"InResponse":true,"InCreate":true,"Description":"檢查圖檔上傳"},{"Name":"memo","ColumnName":"Memo","Type":"String","Length":1000,"IsRequired":false,"InQuery":false,"InResponse":true,"InCreate":true,"Description":"檢查說明"},{"Name":"companyId","ColumnName":"CompanyId","Type":"Long","Length":null,"IsRequired":false,"InQuery":true,"InResponse":false,"InCreate":false,"Description":"公司編號"},{"Name":"tenantId","ColumnName":"TenantId","Type":"Long","Length":null,"IsRequired":false,"InQuery":false,"InResponse":false,"InCreate":false,"Description":"集團編號"}]},{"Name":"CheckRecordItem","TableName":"CheckRecord_Item","Description":"大樓定期檢查紀錄項目明細","HasIHasCompany":true,"HasIHasTenant":true,"Project":null,"IsSync":false,"EntityItems":[{"Name":"checkRecordId","ColumnName":"CheckRecord_Id","Type":"Long","Length":null,"IsRequired":false,"InQuery":true,"InResponse":true,"InCreate":true,"Description":"頭檔ID"},{"Name":"ord","ColumnName":"Ord","Type":"Integer","Length":null,"IsRequired":false,"InQuery":false,"InResponse":true,"InCreate":true,"Description":"順序"},{"Name":"checkSettingBuildingItemId","ColumnName":"CheckSettingBuilding_Item_Id","Type":"Long","Length":null,"IsRequired":false,"InQuery":true,"InResponse":true,"InCreate":true,"Description":"檢查項目ID"},{"Name":"standardValue","ColumnName":"StandardValue","Type":"String","Length":300,"IsRequired":false,"InQuery":false,"InResponse":true,"InCreate":true,"Description":"標準值"},{"Name":"checkValue","ColumnName":"CheckValue","Type":"String","Length":300,"IsRequired":false,"InQuery":false,"InResponse":true,"InCreate":true,"Description":"檢查值"},{"Name":"must","ColumnName":"Must","Type":"Boolean","Length":null,"IsRequired":false,"InQuery":false,"InResponse":true,"InCreate":true,"Description":"必檢查"},{"Name":"codeQualify","ColumnName":"Code_Qualify","Type":"Long","Length":null,"IsRequired":false,"InQuery":true,"InResponse":true,"InCreate":true,"Description":"檢查結果"},{"Name":"fileUploadMapId","ColumnName":"File_UploadMap_Id","Type":"Long","Length":null,"IsRequired":false,"InQuery":false,"InResponse":true,"InCreate":true,"Description":"檢查圖檔上傳"},{"Name":"memo","ColumnName":"Memo","Type":"String","Length":1000,"IsRequired":false,"InQuery":false,"InResponse":true,"InCreate":true,"Description":"檢查說明"},{"Name":"companyId","ColumnName":"CompanyId","Type":"Long","Length":null,"IsRequired":false,"InQuery":true,"InResponse":false,"InCreate":false,"Description":"公司編號"},{"Name":"tenantId","ColumnName":"TenantId","Type":"Long","Length":null,"IsRequired":false,"InQuery":false,"InResponse":false,"InCreate":false,"Description":"集團編號"}]},{"Name":"InformRecord","TableName":"InformRecord","Description":"案件通報","HasIHasCompany":true,"HasIHasTenant":true,"Project":null,"IsSync":false,"EntityItems":[{"Name":"informCode","ColumnName":"InformCode","Type":"String","Length":20,"IsRequired":false,"InQuery":false,"InResponse":true,"InCreate":true,"Description":"通報單號"},{"Name":"buildingId","ColumnName":"Building_Id","Type":"Long","Length":null,"IsRequired":false,"InQuery":true,"InResponse":true,"InCreate":true,"Description":"大樓"},{"Name":"informDate","ColumnName":"InformDate","Type":"Date","Length":null,"IsRequired":false,"InQuery":false,"InResponse":true,"InCreate":true,"Description":"通報日期"},{"Name":"incidentDate","ColumnName":"IncidentDate","Type":"Date","Length":null,"IsRequired":false,"InQuery":false,"InResponse":true,"InCreate":true,"Description":"發生時間"},{"Name":"codeInformTerm","ColumnName":"Code_InformTerm","Type":"Long","Length":null,"IsRequired":false,"InQuery":true,"InResponse":true,"InCreate":true,"Description":"異常類別"},{"Name":"codeInformLevel","ColumnName":"Code_InformLevel","Type":"Long","Length":null,"IsRequired":false,"InQuery":true,"InResponse":true,"InCreate":true,"Description":"案件等級"},{"Name":"publicAreaId","ColumnName":"PublicArea_Id","Type":"Long","Length":null,"IsRequired":false,"InQuery":false,"InResponse":true,"InCreate":true,"Description":"公共空間ID"},{"Name":"houseId","ColumnName":"House_Id","Type":"Long","Length":null,"IsRequired":false,"InQuery":true,"InResponse":true,"InCreate":true,"Description":"戶號"},{"Name":"facilityItemId","ColumnName":"FacilityItem_Id","Type":"Long","Length":null,"IsRequired":false,"InQuery":true,"InResponse":true,"InCreate":true,"Description":"設備ID"},{"Name":"customerId","ColumnName":"Customer_Id","Type":"Long","Length":null,"IsRequired":false,"InQuery":true,"InResponse":true,"InCreate":true,"Description":"客戶"},{"Name":"contact","ColumnName":"Contact","Type":"String","Length":20,"IsRequired":false,"InQuery":false,"InResponse":true,"InCreate":true,"Description":"報案人員"},{"Name":"checkSettingItemId","ColumnName":"CheckSetting_Item_Id","Type":"Long","Length":null,"IsRequired":false,"InQuery":true,"InResponse":true,"InCreate":true,"Description":"通報項目"},{"Name":"codeNoticeMethod","ColumnName":"Code_NoticeMethod","Type":"Long","Length":null,"IsRequired":false,"InQuery":true,"InResponse":true,"InCreate":true,"Description":"緊急通知方式"},{"Name":"description","ColumnName":"Description","Type":"String","Length":1000,"IsRequired":false,"InQuery":false,"InResponse":true,"InCreate":true,"Description":"問題描述"},{"Name":"codeBusinessEffect","ColumnName":"Code_BusinessEffect","Type":"Long","Length":null,"IsRequired":false,"InQuery":true,"InResponse":true,"InCreate":true,"Description":"影響營業"},{"Name":"codeRiskLevel","ColumnName":"Code_RiskLevel","Type":"Long","Length":null,"IsRequired":false,"InQuery":true,"InResponse":true,"InCreate":true,"Description":"風險等級"},{"Name":"codeInformProcess","ColumnName":"Code_InformProcess","Type":"Long","Length":null,"IsRequired":false,"InQuery":true,"InResponse":true,"InCreate":true,"Description":"處理方式"},{"Name":"processingDescription","ColumnName":"ProcessingDescription","Type":"String","Length":1000,"IsRequired":false,"InQuery":false,"InResponse":true,"InCreate":true,"Description":"處置措施"},{"Name":"inReport","ColumnName":"InReport","Type":"Boolean","Length":null,"IsRequired":false,"InQuery":false,"InResponse":true,"InCreate":true,"Description":"列入報告"},{"Name":"fileUploadMapId","ColumnName":"File_UploadMap_Id","Type":"Long","Length":null,"IsRequired":false,"InQuery":false,"InResponse":true,"InCreate":true,"Description":"檔案上傳"},{"Name":"memo","ColumnName":"Memo","Type":"String","Length":1000,"IsRequired":false,"InQuery":false,"InResponse":true,"InCreate":true,"Description":"備註"},{"Name":"checkRecordItemId","ColumnName":"CheckRecord_Item_Id","Type":"Long","Length":null,"IsRequired":false,"InQuery":true,"InResponse":true,"InCreate":true,"Description":"定檢來源ID"},{"Name":"companyId","ColumnName":"CompanyId","Type":"Long","Length":null,"IsRequired":false,"InQuery":true,"InResponse":false,"InCreate":false,"Description":"公司編號"},{"Name":"tenantId","ColumnName":"TenantId","Type":"Long","Length":null,"IsRequired":false,"InQuery":false,"InResponse":false,"InCreate":false,"Description":"集團編號"}]},{"Name":"InformRecordTimeRecord","TableName":"InformRecord_TimeRecord","Description":"案件通報時間紀錄","HasIHasCompany":true,"HasIHasTenant":true,"Project":null,"IsSync":false,"EntityItems":[{"Name":"informRecordId","ColumnName":"InformRecord_Id","Type":"Long","Length":null,"IsRequired":false,"InQuery":true,"InResponse":true,"InCreate":true,"Description":"頭檔ID"},{"Name":"codeInformTimeType","ColumnName":"Code_InformTimeType","Type":"Long","Length":null,"IsRequired":false,"InQuery":true,"InResponse":true,"InCreate":true,"Description":"時間類別"},{"Name":"date","ColumnName":"Date","Type":"Date","Length":null,"IsRequired":false,"InQuery":false,"InResponse":true,"InCreate":true,"Description":"發生時間"},{"Name":"companyId","ColumnName":"CompanyId","Type":"Long","Length":null,"IsRequired":false,"InQuery":true,"InResponse":false,"InCreate":false,"Description":"公司編號"},{"Name":"tenantId","ColumnName":"TenantId","Type":"Long","Length":null,"IsRequired":false,"InQuery":false,"InResponse":false,"InCreate":false,"Description":"集團編號"}]},{"Name":"InformRecordTrack","TableName":"InformRecord_Track","Description":"案件通報處理紀錄","HasIHasCompany":true,"HasIHasTenant":true,"Project":null,"IsSync":false,"EntityItems":[{"Name":"informRecordId","ColumnName":"InformRecord_Id","Type":"Long","Length":null,"IsRequired":false,"InQuery":true,"InResponse":true,"InCreate":true,"Description":"頭檔ID"},{"Name":"date","ColumnName":"Date","Type":"Date","Length":null,"IsRequired":false,"InQuery":false,"InResponse":true,"InCreate":true,"Description":"日期時間"},{"Name":"codeInformRecordStatus","ColumnName":"Code_InformRecordStatus","Type":"Long","Length":null,"IsRequired":false,"InQuery":true,"InResponse":true,"InCreate":true,"Description":"處理狀態"},{"Name":"codeInformProcessingStatus","ColumnName":"Code_InformProcessingStatus","Type":"Long","Length":null,"IsRequired":false,"InQuery":true,"InResponse":true,"InCreate":true,"Description":"處理中進度"},{"Name":"memo","ColumnName":"Memo","Type":"String","Length":1000,"IsRequired":false,"InQuery":false,"InResponse":true,"InCreate":true,"Description":"說明"},{"Name":"fileUploadMapId","ColumnName":"File_UploadMap_Id","Type":"Long","Length":null,"IsRequired":false,"InQuery":false,"InResponse":true,"InCreate":true,"Description":"照片上傳"},{"Name":"companyId","ColumnName":"CompanyId","Type":"Long","Length":null,"IsRequired":false,"InQuery":true,"InResponse":false,"InCreate":false,"Description":"公司編號"},{"Name":"tenantId","ColumnName":"TenantId","Type":"Long","Length":null,"IsRequired":false,"InQuery":false,"InResponse":false,"InCreate":false,"Description":"集團編號"}]},{"Name":"InformRecordTrackFile","TableName":"InformRecord_Track_File","Description":"案件通報處理紀錄附加檔案","HasIHasCompany":true,"HasIHasTenant":true,"Project":null,"IsSync":false,"EntityItems":[{"Name":"informRecordTrackId","ColumnName":"InformRecord_Track_Id","Type":"Long","Length":null,"IsRequired":false,"InQuery":true,"InResponse":true,"InCreate":true,"Description":"頭檔ID"},{"Name":"codeInformFileType","ColumnName":"Code_InformFileType","Type":"Long","Length":null,"IsRequired":false,"InQuery":true,"InResponse":true,"InCreate":true,"Description":"檔案類別"},{"Name":"fileId","ColumnName":"File_Id","Type":"Long","Length":null,"IsRequired":false,"InQuery":false,"InResponse":true,"InCreate":true,"Description":"附檔上傳"},{"Name":"memo","ColumnName":"Memo","Type":"String","Length":1000,"IsRequired":false,"InQuery":false,"InResponse":true,"InCreate":true,"Description":"備註"},{"Name":"companyId","ColumnName":"CompanyId","Type":"Long","Length":null,"IsRequired":false,"InQuery":true,"InResponse":false,"InCreate":false,"Description":"公司編號"},{"Name":"tenantId","ColumnName":"TenantId","Type":"Long","Length":null,"IsRequired":false,"InQuery":false,"InResponse":false,"InCreate":false,"Description":"集團編號"}]},{"Name":"InformRecordTrackGoods","TableName":"InformRecord_Track_Goods","Description":"案件通報商品身檔","HasIHasCompany":true,"HasIHasTenant":true,"Project":null,"IsSync":false,"EntityItems":[{"Name":"informRecordTrackId","ColumnName":"InformRecord_Track_Id","Type":"Long","Length":null,"IsRequired":false,"InQuery":true,"InResponse":true,"InCreate":true,"Description":"頭檔ID"},{"Name":"goodsId","ColumnName":"Goods_Id","Type":"Long","Length":null,"IsRequired":false,"InQuery":true,"InResponse":true,"InCreate":true,"Description":"品項"},{"Name":"qty","ColumnName":"Qty","Type":"Integer","Length":null,"IsRequired":false,"InQuery":false,"InResponse":true,"InCreate":true,"Description":"數量"},{"Name":"costUnitPrice","ColumnName":"CostUnitPrice","Type":"Float","Length":null,"IsRequired":false,"InQuery":false,"InResponse":true,"InCreate":true,"Description":"成本單價"},{"Name":"saleUnitPrice","ColumnName":"SaleUnitPrice","Type":"Float","Length":null,"IsRequired":false,"InQuery":false,"InResponse":true,"InCreate":true,"Description":"銷貨單價"},{"Name":"brand","ColumnName":"Brand","Type":"String","Length":300,"IsRequired":false,"InQuery":false,"InResponse":true,"InCreate":true,"Description":"品牌規格"},{"Name":"memo","ColumnName":"Memo","Type":"String","Length":1000,"IsRequired":false,"InQuery":false,"InResponse":true,"InCreate":true,"Description":"備註"},{"Name":"companyId","ColumnName":"CompanyId","Type":"Long","Length":null,"IsRequired":false,"InQuery":true,"InResponse":false,"InCreate":false,"Description":"公司編號"},{"Name":"tenantId","ColumnName":"TenantId","Type":"Long","Length":null,"IsRequired":false,"InQuery":false,"InResponse":false,"InCreate":false,"Description":"集團編號"}]}]
